ProActiveChatBot/__init__.py
ProActiveChatBot/main.py
ProActiveChatBot-0.0.1.dist-info/METADATA
ProActiveChatBot-0.0.1.dist-info/WHEEL
ProActiveChatBot-0.0.1.dist-info/entry_points.txt
ProActiveChatBot-0.0.1.dist-info/top_level.txt
ProActiveChatBot-0.0.1.dist-info/RECORD
