Metadata-Version: 2.1
Name: ProActiveChatBot
Version: 0.0.1
Summary: make your chatbot become proactive
Author: TienHN
Author-email: tienhn8@fpt.com
Classifier: Programming Language :: Python :: 3
Classifier: License :: OSI Approved :: MIT License
Classifier: Operating System :: OS Independent
Requires-Python: >=3.9
